progai/__init__.py
progai/prg.py
progai-0.1.0.dist-info/METADATA
progai-0.1.0.dist-info/WHEEL
progai-0.1.0.dist-info/top_level.txt
progai-0.1.0.dist-info/RECORD
